htyaml-0.1.0.dist-info/METADATA
htyaml-0.1.0.dist-info/WHEEL
htyaml-0.1.0.dist-info/entry_points.txt
htyaml/__init__.py
htyaml-0.1.0.dist-info/RECORD
